GreenWorksAPI/Enums.py
GreenWorksAPI/GreenWorksAPI.py
GreenWorksAPI/Records.py
GreenWorksAPI/__init__.py
greenworks-0.1.0.0.dist-info/licenses/LICENSE
greenworks-0.1.0.0.dist-info/METADATA
greenworks-0.1.0.0.dist-info/WHEEL
greenworks-0.1.0.0.dist-info/top_level.txt
greenworks-0.1.0.0.dist-info/RECORD
