Metadata-Version: 2.4
Name: GreenWorks
Version: 0.1.0.0
Summary: An API wrapper for the Greenworks robotic lawn mower
Author-email: Christian Boes <boes9@icloud.com>
License-Expression: MIT
Project-URL: Documentation, https://github.com/Boes24/GreenWorks-Core
Project-URL: Issues, https://github.com/Boes24/GreenWorks-Core/issues
Classifier: Programming Language :: Python :: 3
Classifier: Operating System :: OS Independent
Requires-Python: >=3.9
License-File: LICENSE
Dynamic: license-file
